odoo/addons/l10n_br_resource/README.rst
odoo/addons/l10n_br_resource/__init__.py
odoo/addons/l10n_br_resource/__manifest__.py
odoo/addons/l10n_br_resource/i18n/es.po
odoo/addons/l10n_br_resource/i18n/l10n_br_resource.pot
odoo/addons/l10n_br_resource/i18n/pt_BR.po
odoo/addons/l10n_br_resource/models/__init__.py
odoo/addons/l10n_br_resource/models/resource_calendar.py
odoo/addons/l10n_br_resource/models/resource_calendar_leaves.py
odoo/addons/l10n_br_resource/readme/CONFIGURE.md
odoo/addons/l10n_br_resource/readme/CONTRIBUTORS.md
odoo/addons/l10n_br_resource/readme/CREDITS.md
odoo/addons/l10n_br_resource/readme/DESCRIPTION.md
odoo/addons/l10n_br_resource/readme/HISTORY.md
odoo/addons/l10n_br_resource/readme/INSTALL.md
odoo/addons/l10n_br_resource/readme/ROADMAP.md
odoo/addons/l10n_br_resource/readme/USAGE.md
odoo/addons/l10n_br_resource/security/ir.model.access.csv
odoo/addons/l10n_br_resource/static/description/icon.png
odoo/addons/l10n_br_resource/static/description/icon.svg.oca
odoo/addons/l10n_br_resource/static/description/index.html
odoo/addons/l10n_br_resource/tests/__init__.py
odoo/addons/l10n_br_resource/tests/test_resource_calendar.py
odoo/addons/l10n_br_resource/tests/test_resource_calendar_2.py
odoo/addons/l10n_br_resource/tools/__init__.py
odoo/addons/l10n_br_resource/tools/brazil_all_holidays_set.py
odoo/addons/l10n_br_resource/views/resource_calendar_leaves_view.xml
odoo/addons/l10n_br_resource/views/resource_calendar_menu.xml
odoo/addons/l10n_br_resource/views/resource_calendar_view.xml
odoo/addons/l10n_br_resource/wizards/__init__.py
odoo/addons/l10n_br_resource/wizards/workalendar_holiday_import_views.xml
odoo/addons/l10n_br_resource/wizards/workalendar_holiday_import_wizard.py
odoo_addon_l10n_br_resource-16.0.1.1.0.dist-info/METADATA
odoo_addon_l10n_br_resource-16.0.1.1.0.dist-info/WHEEL
odoo_addon_l10n_br_resource-16.0.1.1.0.dist-info/top_level.txt
odoo_addon_l10n_br_resource-16.0.1.1.0.dist-info/RECORD
